{"chunk":9,"numChunks":14,"fileHash":"GjrTswlKssoHZCuceyOswFCfNvQkKDimjfuWae1zK0Y=","filePath":"Packages/packages-lock.json","content":"{\n  \"dependencies\": {\n    \"com.unity.modules.animation\": {\n      \"version\": \"1.0.0\",\n      \"depth\": 0,\n      \"source\": \"builtin\",\n      \"dependencies\": {}\n    },\n    \"com.unity.modules.assetbundle\": {\n      \"version\": \"1.0.0\",\n      \"depth\": 0,\n      \"source\": \"builtin\",\n      \"dependencies\": {}\n    },\n    \"com.unity.modules.audio\": {\n      \"version\": \"1.0.0\",\n      \"depth\": 0,\n      \"source\": \"builtin\",\n      \"dependencies\": {}\n    },\n    \"com.unity.modules.cloth\": {\n      \"version\": \"1.0.0\",\n      \"depth\": 0,\n      \"source\": \"builtin\",\n      \"dependencies\": {\n        \"com.unity.modules.physics\": \"1.0.0\"\n      }\n    },\n    \"com.unity.modules.director\": {\n      \"version\": \"1.0.0\",\n      \"depth\": 0,\n      \"source\": \"builtin\",\n      \"dependencies\": {\n        \"com.unity.modules.audio\": \"1.0.0\",\n        \"com.unity.modules.animation\": \"1.0.0\"\n      }\n    },\n    \"com.unity.modules.imageconversion\": {\n      \"version\": \"1.0.0\",\n      \"depth\": 0,\n      \"source\": \"builtin\",\n      \"dependencies\": {}\n    },\n    \"com.unity.modules.imgui\": {\n      \"version\": \"1.0.0\",\n      \"depth\": 0,\n      \"source\": \"builtin\",\n      \"dependencies\": {}\n    },\n    \"com.unity.modules.jsonserialize\": {\n      \"version\": \"1.0.0\",\n      \"depth\": 0,\n      \"source\": \"builtin\",\n      \"dependencies\": {}\n    },"}